[
  {
    "company": "VK",
    "timeframe": "6_months",
    "title": "Maximize Distance to Closest Person",
    "difficulty": "MEDIUM",
    "link": "https://leetcode.com/problems/maximize-distance-to-closest-person",
    "asked_on": "",
    "tags": [
      "Array"
    ]
  },
  {
    "company": "VK",
    "timeframe": "6_months",
    "title": "Valid Parentheses",
    "difficulty": "EASY",
    "link": "https://leetcode.com/problems/valid-parentheses",
    "asked_on": "",
    "tags": [
      "String",
      "Stack"
    ]
  },
  {
    "company": "VK",
    "timeframe": "more_than_6_months",
    "title": "Merge Sorted Array",
    "difficulty": "EASY",
    "link": "https://leetcode.com/problems/merge-sorted-array",
    "asked_on": "",
    "tags": [
      "Array",
      "Two Pointers",
      "Sorting"
    ]
  },
  {
    "company": "VK",
    "timeframe": "more_than_6_months",
    "title": "Move Zeroes",
    "difficulty": "EASY",
    "link": "https://leetcode.com/problems/move-zeroes",
    "asked_on": "",
    "tags": [
      "Array",
      "Two Pointers"
    ]
  },
  {
    "company": "VK",
    "timeframe": "more_than_6_months",
    "title": "Merge Two Sorted Lists",
    "difficulty": "EASY",
    "link": "https://leetcode.com/problems/merge-two-sorted-lists",
    "asked_on": "",
    "tags": [
      "Linked List",
      "Recursion"
    ]
  },
  {
    "company": "VK",
    "timeframe": "more_than_6_months",
    "title": "Valid Parentheses",
    "difficulty": "EASY",
    "link": "https://leetcode.com/problems/valid-parentheses",
    "asked_on": "",
    "tags": [
      "String",
      "Stack"
    ]
  },
  {
    "company": "VK",
    "timeframe": "more_than_6_months",
    "title": "Maximize Distance to Closest Person",
    "difficulty": "MEDIUM",
    "link": "https://leetcode.com/problems/maximize-distance-to-closest-person",
    "asked_on": "",
    "tags": [
      "Array"
    ]
  },
  {
    "company": "VK",
    "timeframe": "all_time",
    "title": "Move Zeroes",
    "difficulty": "EASY",
    "link": "https://leetcode.com/problems/move-zeroes",
    "asked_on": "",
    "tags": [
      "Array",
      "Two Pointers"
    ]
  },
  {
    "company": "VK",
    "timeframe": "all_time",
    "title": "Maximize Distance to Closest Person",
    "difficulty": "MEDIUM",
    "link": "https://leetcode.com/problems/maximize-distance-to-closest-person",
    "asked_on": "",
    "tags": [
      "Array"
    ]
  },
  {
    "company": "VK",
    "timeframe": "all_time",
    "title": "Valid Parentheses",
    "difficulty": "EASY",
    "link": "https://leetcode.com/problems/valid-parentheses",
    "asked_on": "",
    "tags": [
      "String",
      "Stack"
    ]
  },
  {
    "company": "VK",
    "timeframe": "all_time",
    "title": "Merge Sorted Array",
    "difficulty": "EASY",
    "link": "https://leetcode.com/problems/merge-sorted-array",
    "asked_on": "",
    "tags": [
      "Array",
      "Two Pointers",
      "Sorting"
    ]
  },
  {
    "company": "VK",
    "timeframe": "all_time",
    "title": "Merge Two Sorted Lists",
    "difficulty": "EASY",
    "link": "https://leetcode.com/problems/merge-two-sorted-lists",
    "asked_on": "",
    "tags": [
      "Linked List",
      "Recursion"
    ]
  },
  {
    "company": "VK",
    "timeframe": "all_time",
    "title": "Valid Palindrome",
    "difficulty": "EASY",
    "link": "https://leetcode.com/problems/valid-palindrome",
    "asked_on": "",
    "tags": [
      "Two Pointers",
      "String"
    ]
  }
]